nprim/primo.py
nprim-1.27.dist-info/LICENSE.txt
nprim-1.27.dist-info/METADATA
nprim-1.27.dist-info/WHEEL
nprim-1.27.dist-info/top_level.txt
nprim-1.27.dist-info/RECORD
