Metadata-Version: 2.1
Name: nprim
Version: 1.27
Summary: A tool to find prime numbers
Home-page: UNKNOWN
Author: Rubén Martín
Author-email: rmartinm96@hotmail.com
License: GNU GPLv3
Keywords: primo prime
Platform: UNKNOWN
Classifier: Development Status :: 4 - Beta
Classifier: Intended Audience :: Developers
Classifier: Topic :: Utilities
Classifier: License :: OSI Approved :: GNU General Public License v3 (GPLv3)
Classifier: Programming Language :: Python :: 3
Classifier: Operating System :: OS Independent
